Metadata-Version: 2.1
Name: ncnnqat
Version: 0.1.0
Summary: A ncnn quantization aware training tool on pytorch.
Home-page: https://github.com/ChenShisen/ncnnqat
Author: Shisen Chen
Author-email: napoleo54css@gmail.com
License: MIT
Keywords: ncnnquantization aware training,deep learning,neural network,CNN,machine learning
Platform: UNKNOWN
Classifier: Development Status :: 5 - Production/Stable
Classifier: Intended Audience :: Science/Research
Classifier: Intended Audience :: Developers
Classifier: Topic :: Scientific/Engineering :: Artificial Intelligence
Classifier: Topic :: Software Development :: Libraries :: Python Modules
Classifier: License :: OSI Approved :: MIT License
Classifier: Programming Language :: Python :: 3
Classifier: Programming Language :: Python :: 3.5
Classifier: Programming Language :: Python :: 3.6
Classifier: Programming Language :: Python :: 3.7
Classifier: Programming Language :: Python :: 3.8
Classifier: Programming Language :: Python :: 3 :: Only
Requires-Python: >=3.5, <4
Provides-Extra: test
Provides-Extra: docs
License-File: LICENSE.txt
